pyargcbr/__init__.py
pyargcbr/pyargcbr.py
pyargcbr/agents/__init__.py
pyargcbr/agents/arg_message.py
pyargcbr/agents/argumentation_agent.py
pyargcbr/agents/commitment_store_agent.py
pyargcbr/agents/configuration.py
pyargcbr/agents/debug_agent.py
pyargcbr/agents/metrics.py
pyargcbr/agents/protocol.py
pyargcbr/agents/similarity_algorithms.py
pyargcbr/cbrs/__init__.py
pyargcbr/cbrs/argumentation_cbr.py
pyargcbr/cbrs/cbr.py
pyargcbr/cbrs/domain_cbr.py
pyargcbr/cbrs/lists_operations.py
pyargcbr/configuration/__init__.py
pyargcbr/configuration/configuration_parameters.py
pyargcbr/configuration/settings.py
pyargcbr/knowledge_resources/__init__.py
pyargcbr/knowledge_resources/acceptability_status.py
pyargcbr/knowledge_resources/arg_node.py
pyargcbr/knowledge_resources/argument.py
pyargcbr/knowledge_resources/argument_case.py
pyargcbr/knowledge_resources/argument_justification.py
pyargcbr/knowledge_resources/argument_problem.py
pyargcbr/knowledge_resources/argument_solution.py
pyargcbr/knowledge_resources/argumentation_scheme.py
pyargcbr/knowledge_resources/author.py
pyargcbr/knowledge_resources/case.py
pyargcbr/knowledge_resources/conclusion.py
pyargcbr/knowledge_resources/dialogue.py
pyargcbr/knowledge_resources/dialogue_graph.py
pyargcbr/knowledge_resources/domain_case.py
pyargcbr/knowledge_resources/domain_context.py
pyargcbr/knowledge_resources/group.py
pyargcbr/knowledge_resources/justification.py
pyargcbr/knowledge_resources/norm.py
pyargcbr/knowledge_resources/position.py
pyargcbr/knowledge_resources/premise.py
pyargcbr/knowledge_resources/problem.py
pyargcbr/knowledge_resources/similar_argument_case.py
pyargcbr/knowledge_resources/similar_case.py
pyargcbr/knowledge_resources/similar_domain_case.py
pyargcbr/knowledge_resources/social_context.py
pyargcbr/knowledge_resources/social_entity.py
pyargcbr/knowledge_resources/solution.py
pyargcbr/knowledge_resources/support_set.py
pyargcbr/knowledge_resources/valpref.py
pyargcbr-0.2.5.dist-info/AUTHORS.rst
pyargcbr-0.2.5.dist-info/LICENSE
pyargcbr-0.2.5.dist-info/METADATA
pyargcbr-0.2.5.dist-info/WHEEL
pyargcbr-0.2.5.dist-info/top_level.txt
pyargcbr-0.2.5.dist-info/RECORD
