Metadata-Version: 2.1
Name: pyargcbr
Version: 0.2.5
Summary: Case-Based Argumentation Infrastructure in Python
Home-page: https://github.com/jaumejordan/pyargcbr
Author: Jaume Jordan
Author-email: jjordan@dsic.upv.es
License: MIT license
Keywords: pyargcbr
Platform: UNKNOWN
Classifier: Development Status :: 2 - Pre-Alpha
Classifier: Intended Audience :: Developers
Classifier: License :: OSI Approved :: MIT License
Classifier: Natural Language :: English
Classifier: Programming Language :: Python :: 3.7
Classifier: Programming Language :: Python :: 3.8
Requires-Python: >=3.7
Requires-Dist: spade
Requires-Dist: loguru
